sten_gui/__init__.py
sten_gui/__main__.py
sten_gui/config.py
sten_gui/consts.py
sten_gui/crypto.py
sten_gui/data.py
sten_gui/error.py
sten_gui/icons.py
sten_gui/utils.py
sten_gui/version.py
sten_gui-0.0.3.dist-info/LICENSE
sten_gui-0.0.3.dist-info/METADATA
sten_gui-0.0.3.dist-info/WHEEL
sten_gui-0.0.3.dist-info/entry_points.txt
sten_gui-0.0.3.dist-info/top_level.txt
sten_gui-0.0.3.dist-info/RECORD
