Metadata-Version: 2.1
Name: sten-gui
Version: 0.0.3
Summary: LSB-based image steganography tool
Author: Serhat Çelik
License: GNU GENERAL PUBLIC LICENSE
Keywords: cryptography,steganography
Classifier: Development Status :: 5 - Production/Stable
Classifier: Intended Audience :: Information Technology
Classifier: License :: OSI Approved :: GNU General Public License v3 (GPLv3)
Classifier: Programming Language :: Python :: 3
Classifier: Programming Language :: Python :: 3 :: Only
Classifier: Topic :: Scientific/Engineering :: Image Processing
Classifier: Topic :: Security
Classifier: Topic :: Security :: Cryptography
Requires-Python: ~=3.9
License-File: LICENSE
Requires-Dist: defusedxml
Requires-Dist: numpy
Requires-Dist: Pillow
